{"created_at":"Fri Nov 11 16:39:30 +0000 2011","id":135033923947347968,"id_str":"135033923947347968","text":"#RLfact: I'm diagnosed with depression.","truncated":false,"entities":{"hashtags":[{"text":"RLfact","indices":[0,7]}],"symbols":[],"user_mentions":[],"urls":[]},"source":"\u003ca href=\"http:\/\/mobile.twitter.com\" rel=\"nofollow\"\u003eMobile Web\u003c\/a\u003e","in_reply_to_status_id":null,"in_reply_to_status_id_str":null,"in_reply_to_user_id":null,"in_reply_to_user_id_str":null,"in_reply_to_screen_name":null,"user":{"id":270116953,"id_str":"270116953","name":"inactive","screen_name":"GooberCriss","location":"L.A.","description":"","url":null,"entities":{"description":{"urls":[]}},"protected":false,"followers_count":248,"friends_count":8,"listed_count":4,"created_at":"Tue Mar 22 01:11:12 +0000 2011","favourites_count":372,"utc_offset":-18000,"time_zone":"Quito","geo_enabled":false,"verified":false,"statuses_count":13831,"lang":"en","contributors_enabled":false,"is_translator":false,"is_translation_enabled":false,"profile_background_color":"050505","profile_background_image_url":"http:\/\/pbs.twimg.com\/profile_background_images\/726640360\/1da0d980007c255842a078bea5ce95c8.jpeg","profile_background_image_url_https":"https:\/\/pbs.twimg.com\/profile_background_images\/726640360\/1da0d980007c255842a078bea5ce95c8.jpeg","profile_background_tile":false,"profile_image_url":"http:\/\/pbs.twimg.com\/profile_images\/463199235588894720\/WuKEtCv8_normal.jpeg","profile_image_url_https":"https:\/\/pbs.twimg.com\/profile_images\/463199235588894720\/WuKEtCv8_normal.jpeg","profile_link_color":"706E6F","profile_sidebar_border_color":"000000","profile_sidebar_fill_color":"252429","profile_text_color":"666666","profile_use_background_image":false,"has_extended_profile":false,"default_profile":false,"default_profile_image":false,"following":false,"follow_request_sent":false,"notifications":false,"translator_type":"none"},"geo":null,"coordinates":null,"place":null,"contributors":null,"is_quote_status":false,"retweet_count":0,"favorite_count":0,"favorited":false,"retweeted":false,"lang":"en"}
