{"created_at":"Sat Nov 26 02:27:14 +0000 2011","id":140255258193559552,"id_str":"140255258193559552","text":"Open Question: How to get rid of depression naturally?: I have been diagnosed with depression and it is getting... *http:\/\/t.co\/SG5ocheR","truncated":false,"entities":{"hashtags":[],"symbols":[],"user_mentions":[],"urls":[{"url":"http:\/\/t.co\/SG5ocheR","expanded_url":"http:\/\/yhoo.it\/ukSbmM","display_url":"yhoo.it\/ukSbmM","indices":[116,136]}]},"source":"\u003ca href=\"http:\/\/hellotxt.com\" rel=\"nofollow\"\u003ehellotxt.com\u003c\/a\u003e","in_reply_to_status_id":null,"in_reply_to_status_id_str":null,"in_reply_to_user_id":null,"in_reply_to_user_id_str":null,"in_reply_to_screen_name":null,"user":{"id":299286434,"id_str":"299286434","name":"Brand Fashion","screen_name":"MyBrandsFashion","location":"www","description":"My fashion blog and style. My new look and dress for less. Top fashion. Top brands. Top designers. Coupons.","url":"http:\/\/t.co\/kKlPWYVcxs","entities":{"url":{"urls":[{"url":"http:\/\/t.co\/kKlPWYVcxs","expanded_url":"http:\/\/www.brandsfashion.net","display_url":"brandsfashion.net","indices":[0,22]}]},"description":{"urls":[]}},"protected":false,"followers_count":1203,"friends_count":564,"listed_count":50,"created_at":"Sun May 15 20:27:10 +0000 2011","favourites_count":0,"utc_offset":7200,"time_zone":"Athens","geo_enabled":false,"verified":false,"statuses_count":188589,"lang":"en","contributors_enabled":false,"is_translator":false,"is_translation_enabled":false,"profile_background_color":"FF6699","profile_background_image_url":"http:\/\/pbs.twimg.com\/profile_background_images\/253935206\/brandsfashion_twitter.jpg","profile_background_image_url_https":"https:\/\/pbs.twimg.com\/profile_background_images\/253935206\/brandsfashion_twitter.jpg","profile_background_tile":true,"profile_image_url":"http:\/\/pbs.twimg.com\/profile_images\/1355044150\/dior_normal.jpg","profile_image_url_https":"https:\/\/pbs.twimg.com\/profile_images\/1355044150\/dior_normal.jpg","profile_link_color":"B40B43","profile_sidebar_border_color":"CC3366","profile_sidebar_fill_color":"E5507E","profile_text_color":"362720","profile_use_background_image":true,"has_extended_profile":false,"default_profile":false,"default_profile_image":false,"following":false,"follow_request_sent":false,"notifications":false,"translator_type":"none"},"geo":null,"coordinates":null,"place":null,"contributors":null,"is_quote_status":false,"retweet_count":0,"favorite_count":0,"favorited":false,"retweeted":false,"possibly_sensitive":false,"possibly_sensitive_appealable":false,"lang":"en"}
