{"created_at":"Mon Dec 24 01:48:54 +0000 2012","id":283026430273671169,"id_str":"283026430273671169","text":"I have been diagnosed with depression and bi-polar im taken my meds so I can't help how I come off","truncated":false,"entities":{"hashtags":[],"symbols":[],"user_mentions":[],"urls":[]},"source":"\u003ca href=\"http:\/\/www.twitter.com\" rel=\"nofollow\"\u003eTwitter for Windows Phone\u003c\/a\u003e","in_reply_to_status_id":null,"in_reply_to_status_id_str":null,"in_reply_to_user_id":null,"in_reply_to_user_id_str":null,"in_reply_to_screen_name":null,"user":{"id":147701288,"id_str":"147701288","name":".:Marolynn_Monroe:.","screen_name":"iDntLikeYou_","location":"\\ \\      \u30ce Georgia!!!!","description":"\u2022 #teampisces\u2653; \u2022 #teamSINGLE; \u2022#teamfemm\u2640; \u2022s.c.:stasiaily; \u2022instagram: _stasia_world_; \u2022kik me: marolynn_monroe","url":null,"entities":{"description":{"urls":[]}},"protected":false,"followers_count":163,"friends_count":164,"listed_count":1,"created_at":"Mon May 24 20:47:56 +0000 2010","favourites_count":22,"utc_offset":-21600,"time_zone":"Central Time (US & Canada)","geo_enabled":false,"verified":false,"statuses_count":9473,"lang":"en","contributors_enabled":false,"is_translator":false,"is_translation_enabled":false,"profile_background_color":"ACDED6","profile_background_image_url":"http:\/\/abs.twimg.com\/images\/themes\/theme18\/bg.gif","profile_background_image_url_https":"https:\/\/abs.twimg.com\/images\/themes\/theme18\/bg.gif","profile_background_tile":true,"profile_image_url":"http:\/\/pbs.twimg.com\/profile_images\/621464253564907520\/LEV7owlY_normal.jpg","profile_image_url_https":"https:\/\/pbs.twimg.com\/profile_images\/621464253564907520\/LEV7owlY_normal.jpg","profile_link_color":"038543","profile_sidebar_border_color":"EEEEEE","profile_sidebar_fill_color":"F6F6F6","profile_text_color":"333333","profile_use_background_image":true,"has_extended_profile":false,"default_profile":false,"default_profile_image":false,"following":false,"follow_request_sent":false,"notifications":false,"translator_type":"none"},"geo":null,"coordinates":null,"place":null,"contributors":null,"is_quote_status":false,"retweet_count":0,"favorite_count":0,"favorited":false,"retweeted":false,"lang":"en"}
