{"created_at":"Tue Aug 12 01:07:53 +0000 2014","id":498999276903866369,"id_str":"498999276903866369","text":"@Luke5SOS ne gives 2 shits about me. I just sometimes feel like no one would even care if I died. I'm diagnosed with severe depression, anx+","truncated":false,"entities":{"hashtags":[],"symbols":[],"user_mentions":[{"screen_name":"Luke5SOS","name":"Luke Hemmings","id":403245020,"id_str":"403245020","indices":[0,9]}],"urls":[]},"source":"\u003ca href=\"http:\/\/twitter.com\/download\/iphone\" rel=\"nofollow\"\u003eTwitter for iPhone\u003c\/a\u003e","in_reply_to_status_id":498999099702923265,"in_reply_to_status_id_str":"498999099702923265","in_reply_to_user_id":2720101067,"in_reply_to_user_id_str":"2720101067","in_reply_to_screen_name":"hyfrhemmiings","user":{"id":2720101067,"id_str":"2720101067","name":"jasmine \u2661","screen_name":"hyfrhemmiings","location":"I saw them \/\/ harry noticed","description":"\u263d 10\/10 do not recommend 5sos \u263e","url":"http:\/\/t.co\/NCDxXFtmMZ","entities":{"url":{"urls":[{"url":"http:\/\/t.co\/NCDxXFtmMZ","expanded_url":"http:\/\/Instagram.com\/lashtonship","display_url":"Instagram.com\/lashtonship","indices":[0,22]}]},"description":{"urls":[]}},"protected":false,"followers_count":680,"friends_count":1828,"listed_count":8,"created_at":"Mon Jul 21 21:18:07 +0000 2014","favourites_count":1891,"utc_offset":null,"time_zone":null,"geo_enabled":false,"verified":false,"statuses_count":2730,"lang":"en","contributors_enabled":false,"is_translator":false,"is_translation_enabled":false,"profile_background_color":"C0DEED","profile_background_image_url":"http:\/\/abs.twimg.com\/images\/themes\/theme1\/bg.png","profile_background_image_url_https":"https:\/\/abs.twimg.com\/images\/themes\/theme1\/bg.png","profile_background_tile":false,"profile_image_url":"http:\/\/pbs.twimg.com\/profile_images\/502523137624666113\/KVZR2RqK_normal.jpeg","profile_image_url_https":"https:\/\/pbs.twimg.com\/profile_images\/502523137624666113\/KVZR2RqK_normal.jpeg","profile_banner_url":"https:\/\/pbs.twimg.com\/profile_banners\/2720101067\/1408645828","profile_link_color":"1DA1F2","profile_sidebar_border_color":"C0DEED","profile_sidebar_fill_color":"DDEEF6","profile_text_color":"333333","profile_use_background_image":true,"has_extended_profile":false,"default_profile":true,"default_profile_image":false,"following":false,"follow_request_sent":false,"notifications":false,"translator_type":"none"},"geo":null,"coordinates":null,"place":null,"contributors":null,"is_quote_status":false,"retweet_count":0,"favorite_count":0,"favorited":false,"retweeted":false,"lang":"en"}
