{"created_at":"Tue Dec 30 09:28:14 +0000 2014","id":549859496206405632,"id_str":"549859496206405632","text":"Great I'm diagnosed with severe depression and anxiety","truncated":false,"entities":{"hashtags":[],"symbols":[],"user_mentions":[],"urls":[]},"source":"\u003ca href=\"http:\/\/twitter.com\/#!\/download\/ipad\" rel=\"nofollow\"\u003eTwitter for iPad\u003c\/a\u003e","in_reply_to_status_id":null,"in_reply_to_status_id_str":null,"in_reply_to_user_id":null,"in_reply_to_user_id_str":null,"in_reply_to_screen_name":null,"user":{"id":1588993464,"id_str":"1588993464","name":"\u262aShelby\u262a","screen_name":"DRVGGEDJACKS","location":"Mayer, Arizona","description":"FFA Kid","url":null,"entities":{"description":{"urls":[]}},"protected":false,"followers_count":1088,"friends_count":2074,"listed_count":3,"created_at":"Fri Jul 12 17:40:49 +0000 2013","favourites_count":4178,"utc_offset":-25200,"time_zone":"Arizona","geo_enabled":true,"verified":false,"statuses_count":22292,"lang":"en","contributors_enabled":false,"is_translator":false,"is_translation_enabled":false,"profile_background_color":"9266CC","profile_background_image_url":"http:\/\/pbs.twimg.com\/profile_background_images\/629376062317850624\/cYv9P_26.jpg","profile_background_image_url_https":"https:\/\/pbs.twimg.com\/profile_background_images\/629376062317850624\/cYv9P_26.jpg","profile_background_tile":true,"profile_image_url":"http:\/\/pbs.twimg.com\/profile_images\/775059014589616128\/Z_8z76GK_normal.jpg","profile_image_url_https":"https:\/\/pbs.twimg.com\/profile_images\/775059014589616128\/Z_8z76GK_normal.jpg","profile_banner_url":"https:\/\/pbs.twimg.com\/profile_banners\/1588993464\/1472781876","profile_link_color":"DD2E44","profile_sidebar_border_color":"FFFFFF","profile_sidebar_fill_color":"7AC3EE","profile_text_color":"3D1957","profile_use_background_image":true,"has_extended_profile":false,"default_profile":false,"default_profile_image":false,"following":false,"follow_request_sent":false,"notifications":false,"translator_type":"regular"},"geo":{"type":"Point","coordinates":[34.39812293,-112.23905613]},"coordinates":{"type":"Point","coordinates":[-112.23905613,34.39812293]},"place":{"id":"a612c69b44b2e5da","url":"https:\/\/api.twitter.com\/1.1\/geo\/id\/a612c69b44b2e5da.json","place_type":"admin","name":"Arizona","full_name":"Arizona, USA","country_code":"US","country":"United States","contained_within":[],"bounding_box":{"type":"Polygon","coordinates":[[[-114.818269,31.3322463],[-109.0451527,31.3322463],[-109.0451527,37.004261],[-114.818269,37.004261]]]},"attributes":{}},"contributors":null,"is_quote_status":false,"retweet_count":0,"favorite_count":0,"favorited":false,"retweeted":false,"lang":"en"}
