{"created_at":"Wed Jan 28 15:56:24 +0000 2015","id":560466431213854720,"id_str":"560466431213854720","text":"I was diagnosed with depression &amp; anxiety 2 years ago- it gets better whether u think it will or not. Just keep ur head up  #BellLetsTalk","truncated":false,"entities":{"hashtags":[{"text":"BellLetsTalk","indices":[128,141]}],"symbols":[],"user_mentions":[],"urls":[]},"source":"\u003ca href=\"http:\/\/twitter.com\/download\/android\" rel=\"nofollow\"\u003eTwitter for Android\u003c\/a\u003e","in_reply_to_status_id":null,"in_reply_to_status_id_str":null,"in_reply_to_user_id":null,"in_reply_to_user_id_str":null,"in_reply_to_screen_name":null,"user":{"id":519014809,"id_str":"519014809","name":"trash ketchum","screen_name":"lissil_","location":"","description":"\u2022  lvl20  \u2022 \npsw  \u2022  \ni want to float through life gracefully but i am made of chaos   \u2022","url":null,"entities":{"description":{"urls":[]}},"protected":false,"followers_count":420,"friends_count":393,"listed_count":5,"created_at":"Fri Mar 09 00:12:09 +0000 2012","favourites_count":23139,"utc_offset":-18000,"time_zone":"Eastern Time (US & Canada)","geo_enabled":true,"verified":false,"statuses_count":47555,"lang":"en","contributors_enabled":false,"is_translator":false,"is_translation_enabled":false,"profile_background_color":"000000","profile_background_image_url":"http:\/\/pbs.twimg.com\/profile_background_images\/766705726\/5149e02a0ef8ad2737c114da2f191727.jpeg","profile_background_image_url_https":"https:\/\/pbs.twimg.com\/profile_background_images\/766705726\/5149e02a0ef8ad2737c114da2f191727.jpeg","profile_background_tile":true,"profile_image_url":"http:\/\/pbs.twimg.com\/profile_images\/801331215458508800\/VVEByEGJ_normal.jpg","profile_image_url_https":"https:\/\/pbs.twimg.com\/profile_images\/801331215458508800\/VVEByEGJ_normal.jpg","profile_banner_url":"https:\/\/pbs.twimg.com\/profile_banners\/519014809\/1470509652","profile_link_color":"B30000","profile_sidebar_border_color":"FFFFFF","profile_sidebar_fill_color":"000B17","profile_text_color":"448668","profile_use_background_image":false,"has_extended_profile":true,"default_profile":false,"default_profile_image":false,"following":false,"follow_request_sent":false,"notifications":false,"translator_type":"none"},"geo":null,"coordinates":null,"place":null,"contributors":null,"is_quote_status":false,"retweet_count":0,"favorite_count":1,"favorited":false,"retweeted":false,"lang":"en"}
