{"created_at":"Tue Mar 24 02:47:31 +0000 2015","id":580199231731818496,"id_str":"580199231731818496","text":"little does she know i was diagnosed with depression last year lmao \ud83d\ude1c\ud83d\ude1c","truncated":false,"entities":{"hashtags":[],"symbols":[],"user_mentions":[],"urls":[]},"source":"\u003ca href=\"http:\/\/twitter.com\/download\/iphone\" rel=\"nofollow\"\u003eTwitter for iPhone\u003c\/a\u003e","in_reply_to_status_id":null,"in_reply_to_status_id_str":null,"in_reply_to_user_id":null,"in_reply_to_user_id_str":null,"in_reply_to_screen_name":null,"user":{"id":1639571665,"id_str":"1639571665","name":"eva","screen_name":"BlEBERSAVAGE","location":"","description":"i actually stan ian somerhalder","url":"https:\/\/t.co\/VbSNJtduvC","entities":{"url":{"urls":[{"url":"https:\/\/t.co\/VbSNJtduvC","expanded_url":"https:\/\/twitter.com\/zaynmalik\/status\/433012329803169792","display_url":"twitter.com\/zaynmalik\/stat\u2026","indices":[0,23]}]},"description":{"urls":[]}},"protected":false,"followers_count":2867,"friends_count":35,"listed_count":26,"created_at":"Fri Aug 02 04:13:14 +0000 2013","favourites_count":24870,"utc_offset":-18000,"time_zone":"Eastern Time (US & Canada)","geo_enabled":true,"verified":false,"statuses_count":46487,"lang":"en","contributors_enabled":false,"is_translator":false,"is_translation_enabled":false,"profile_background_color":"EBC1EA","profile_background_image_url":"http:\/\/pbs.twimg.com\/profile_background_images\/528721367366000641\/8Qs1bnVp.jpeg","profile_background_image_url_https":"https:\/\/pbs.twimg.com\/profile_background_images\/528721367366000641\/8Qs1bnVp.jpeg","profile_background_tile":true,"profile_image_url":"http:\/\/pbs.twimg.com\/profile_images\/770140480415956992\/E6AZ3Qhs_normal.jpg","profile_image_url_https":"https:\/\/pbs.twimg.com\/profile_images\/770140480415956992\/E6AZ3Qhs_normal.jpg","profile_banner_url":"https:\/\/pbs.twimg.com\/profile_banners\/1639571665\/1472450775","profile_link_color":"4741EB","profile_sidebar_border_color":"FFFFFF","profile_sidebar_fill_color":"DDEEF6","profile_text_color":"0084B4","profile_use_background_image":true,"has_extended_profile":true,"default_profile":false,"default_profile_image":false,"following":false,"follow_request_sent":false,"notifications":false,"translator_type":"none"},"geo":null,"coordinates":null,"place":null,"contributors":null,"is_quote_status":false,"retweet_count":0,"favorite_count":0,"favorited":false,"retweeted":false,"lang":"en"}
