{"created_at":"Mon Apr 13 05:28:29 +0000 2015","id":587487500895002624,"id_str":"587487500895002624","text":"@waniardy I was diagnosed with depression 5 years ago.  Many people think I'm faking it.  It hurts when people don't want to understand.","truncated":false,"entities":{"hashtags":[],"symbols":[],"user_mentions":[{"screen_name":"waniardy","name":"Wani Ardy #RumahIpoh","id":528293733,"id_str":"528293733","indices":[0,9]}],"urls":[]},"source":"\u003ca href=\"http:\/\/twitter.com\/download\/android\" rel=\"nofollow\"\u003eTwitter for Android\u003c\/a\u003e","in_reply_to_status_id":587485644760285184,"in_reply_to_status_id_str":"587485644760285184","in_reply_to_user_id":528293733,"in_reply_to_user_id_str":"528293733","in_reply_to_screen_name":"waniardy","user":{"id":233206749,"id_str":"233206749","name":"azza azman","screen_name":"azzaazman","location":"Kuala Lumpur","description":"Nope.","url":"https:\/\/t.co\/WziO7Pngpg","entities":{"url":{"urls":[{"url":"https:\/\/t.co\/WziO7Pngpg","expanded_url":"http:\/\/azzafiera.blogspot.com","display_url":"azzafiera.blogspot.com","indices":[0,23]}]},"description":{"urls":[]}},"protected":false,"followers_count":444,"friends_count":567,"listed_count":10,"created_at":"Sun Jan 02 16:17:23 +0000 2011","favourites_count":2935,"utc_offset":28800,"time_zone":"Kuala Lumpur","geo_enabled":true,"verified":false,"statuses_count":48822,"lang":"en","contributors_enabled":false,"is_translator":false,"is_translation_enabled":false,"profile_background_color":"DBE9ED","profile_background_image_url":"http:\/\/pbs.twimg.com\/profile_background_images\/459986432078004224\/r3_X-_yM.jpeg","profile_background_image_url_https":"https:\/\/pbs.twimg.com\/profile_background_images\/459986432078004224\/r3_X-_yM.jpeg","profile_background_tile":true,"profile_image_url":"http:\/\/pbs.twimg.com\/profile_images\/721368167973425153\/8zv-exfY_normal.jpg","profile_image_url_https":"https:\/\/pbs.twimg.com\/profile_images\/721368167973425153\/8zv-exfY_normal.jpg","profile_banner_url":"https:\/\/pbs.twimg.com\/profile_banners\/233206749\/1460910902","profile_link_color":"CC3366","profile_sidebar_border_color":"FFFFFF","profile_sidebar_fill_color":"E6F6F9","profile_text_color":"333333","profile_use_background_image":true,"has_extended_profile":true,"default_profile":false,"default_profile_image":false,"following":false,"follow_request_sent":false,"notifications":false,"translator_type":"none"},"geo":null,"coordinates":null,"place":null,"contributors":null,"is_quote_status":false,"retweet_count":0,"favorite_count":1,"favorited":false,"retweeted":false,"lang":"en"}
