{"created_at":"Tue Mar 01 13:45:11 +0000 2016","id":704663780580573184,"id_str":"704663780580573184","text":"@jasperpines I was diagnosed w\/anxiety over a decade ago. Currently off work due to it &amp; depression. HATE when ppl say they've got SA &gt;","truncated":false,"entities":{"hashtags":[],"symbols":[],"user_mentions":[],"urls":[]},"source":"\u003ca href=\"http:\/\/twitter.com\/download\/iphone\" rel=\"nofollow\"\u003eTwitter for iPhone\u003c\/a\u003e","in_reply_to_status_id":704657201886011392,"in_reply_to_status_id_str":"704657201886011392","in_reply_to_user_id":1411707336,"in_reply_to_user_id_str":"1411707336","in_reply_to_screen_name":"sunrisejehan","user":{"id":34852703,"id_str":"34852703","name":"Emily","screen_name":"poteidia","location":"UK","description":"Fangirl. Gamer. Kindness advocate. Old as balls. #IStandAgainstBullies\n\n(Header art by https:\/\/t.co\/zFdLz9LLrb)","url":"https:\/\/t.co\/mS1S2Yrv3A","entities":{"url":{"urls":[{"url":"https:\/\/t.co\/mS1S2Yrv3A","expanded_url":"http:\/\/poteidia.tumblr.com","display_url":"poteidia.tumblr.com","indices":[0,23]}]},"description":{"urls":[{"url":"https:\/\/t.co\/zFdLz9LLrb","expanded_url":"http:\/\/sorry-so-sorry.tumblr.com\/","display_url":"sorry-so-sorry.tumblr.com","indices":[87,110]}]}},"protected":false,"followers_count":318,"friends_count":603,"listed_count":7,"created_at":"Fri Apr 24 04:57:18 +0000 2009","favourites_count":10182,"utc_offset":0,"time_zone":"London","geo_enabled":false,"verified":false,"statuses_count":13603,"lang":"en","contributors_enabled":false,"is_translator":false,"is_translation_enabled":false,"profile_background_color":"B2DFDA","profile_background_image_url":"http:\/\/abs.twimg.com\/images\/themes\/theme13\/bg.gif","profile_background_image_url_https":"https:\/\/abs.twimg.com\/images\/themes\/theme13\/bg.gif","profile_background_tile":false,"profile_image_url":"http:\/\/pbs.twimg.com\/profile_images\/706499231285006337\/V--2BYLS_normal.jpg","profile_image_url_https":"https:\/\/pbs.twimg.com\/profile_images\/706499231285006337\/V--2BYLS_normal.jpg","profile_banner_url":"https:\/\/pbs.twimg.com\/profile_banners\/34852703\/1458297153","profile_link_color":"93A644","profile_sidebar_border_color":"EEEEEE","profile_sidebar_fill_color":"FFFFFF","profile_text_color":"333333","profile_use_background_image":true,"has_extended_profile":false,"default_profile":false,"default_profile_image":false,"following":false,"follow_request_sent":false,"notifications":false,"translator_type":"none"},"geo":null,"coordinates":null,"place":null,"contributors":null,"is_quote_status":false,"retweet_count":0,"favorite_count":0,"favorited":false,"retweeted":false,"lang":"en"}
