{"created_at":"Fri Apr 08 05:56:46 +0000 2016","id":718316637712183302,"id_str":"718316637712183302","text":"@georgemalik it sucks. The depression, before I was diagnosed and treated, was killer. And the Wings don't help on the anxiety front!","truncated":false,"entities":{"hashtags":[],"symbols":[],"user_mentions":[{"screen_name":"georgemalik","name":"George Malik","id":18213989,"id_str":"18213989","indices":[0,12]}],"urls":[]},"source":"\u003ca href=\"http:\/\/www.tweetcaster.com\" rel=\"nofollow\"\u003eTweetCaster for Android\u003c\/a\u003e","in_reply_to_status_id":718316349114748928,"in_reply_to_status_id_str":"718316349114748928","in_reply_to_user_id":18213989,"in_reply_to_user_id_str":"18213989","in_reply_to_screen_name":"georgemalik","user":{"id":2324441575,"id_str":"2324441575","name":"nap-a-palooza","screen_name":"annabeth5","location":"","description":"","url":null,"entities":{"description":{"urls":[]}},"protected":false,"followers_count":14,"friends_count":77,"listed_count":0,"created_at":"Sun Feb 02 22:24:08 +0000 2014","favourites_count":1136,"utc_offset":null,"time_zone":null,"geo_enabled":false,"verified":false,"statuses_count":3951,"lang":"en","contributors_enabled":false,"is_translator":false,"is_translation_enabled":false,"profile_background_color":"C0DEED","profile_background_image_url":"http:\/\/abs.twimg.com\/images\/themes\/theme1\/bg.png","profile_background_image_url_https":"https:\/\/abs.twimg.com\/images\/themes\/theme1\/bg.png","profile_background_tile":false,"profile_image_url":"http:\/\/pbs.twimg.com\/profile_images\/658273740128698368\/VazokjYa_normal.jpg","profile_image_url_https":"https:\/\/pbs.twimg.com\/profile_images\/658273740128698368\/VazokjYa_normal.jpg","profile_link_color":"1DA1F2","profile_sidebar_border_color":"C0DEED","profile_sidebar_fill_color":"DDEEF6","profile_text_color":"333333","profile_use_background_image":true,"has_extended_profile":false,"default_profile":true,"default_profile_image":false,"following":false,"follow_request_sent":false,"notifications":false,"translator_type":"none"},"geo":null,"coordinates":null,"place":null,"contributors":null,"is_quote_status":false,"retweet_count":0,"favorite_count":0,"favorited":false,"retweeted":false,"lang":"en"}
