{"created_at":"Thu Jan 12 08:13:09 +0000 2017","id":819457175152193536,"id_str":"819457175152193536","text":"A new favorite: REALITYCHECK - Untitled Love - Unknown To The Unknown by @djhausuttu https:\/\/t.co\/jrs6Awbtl9 on #SoundCloud","truncated":false,"entities":{"hashtags":[{"text":"SoundCloud","indices":[112,123]}],"symbols":[],"user_mentions":[{"screen_name":"djhausUTTU","name":"DJ HAUS\u2708\ufe0f","id":48316732,"id_str":"48316732","indices":[73,84]}],"urls":[{"url":"https:\/\/t.co\/jrs6Awbtl9","expanded_url":"https:\/\/soundcloud.com\/djhausuttu\/realitycheck-untitled-love-unknown-to-the-unknown","display_url":"soundcloud.com\/djhausuttu\/rea\u2026","indices":[85,108]}]},"source":"\u003ca href=\"http:\/\/soundcloud.com\" rel=\"nofollow\"\u003eSoundCloud\u003c\/a\u003e","in_reply_to_status_id":null,"in_reply_to_status_id_str":null,"in_reply_to_user_id":null,"in_reply_to_user_id_str":null,"in_reply_to_screen_name":null,"user":{"id":2683085290,"id_str":"2683085290","name":"E v i l s","screen_name":"AlexDarkDays","location":"Birmingham, England","description":"Birmingham musician and producer. https:\/\/t.co\/7d36PRzYDd","url":"https:\/\/t.co\/7d36PRzYDd","entities":{"url":{"urls":[{"url":"https:\/\/t.co\/7d36PRzYDd","expanded_url":"http:\/\/www.soundcloud.com\/evilsss","display_url":"soundcloud.com\/evilsss","indices":[0,23]}]},"description":{"urls":[{"url":"https:\/\/t.co\/7d36PRzYDd","expanded_url":"http:\/\/www.soundcloud.com\/evilsss","display_url":"soundcloud.com\/evilsss","indices":[34,57]}]}},"protected":false,"followers_count":103,"friends_count":244,"listed_count":2,"created_at":"Mon Jul 07 11:24:06 +0000 2014","favourites_count":197,"utc_offset":null,"time_zone":null,"geo_enabled":true,"verified":false,"statuses_count":284,"lang":"en","contributors_enabled":false,"is_translator":false,"is_translation_enabled":false,"profile_background_color":"000000","profile_background_image_url":"http:\/\/abs.twimg.com\/images\/themes\/theme1\/bg.png","profile_background_image_url_https":"https:\/\/abs.twimg.com\/images\/themes\/theme1\/bg.png","profile_background_tile":false,"profile_image_url":"http:\/\/pbs.twimg.com\/profile_images\/747525875273437184\/EbbpmlUy_normal.jpg","profile_image_url_https":"https:\/\/pbs.twimg.com\/profile_images\/747525875273437184\/EbbpmlUy_normal.jpg","profile_banner_url":"https:\/\/pbs.twimg.com\/profile_banners\/2683085290\/1467059030","profile_link_color":"89C9FA","profile_sidebar_border_color":"000000","profile_sidebar_fill_color":"000000","profile_text_color":"000000","profile_use_background_image":false,"has_extended_profile":false,"default_profile":false,"default_profile_image":false,"following":false,"follow_request_sent":false,"notifications":false,"translator_type":"none"},"geo":null,"coordinates":null,"place":null,"contributors":null,"is_quote_status":false,"retweet_count":1,"favorite_count":2,"favorited":false,"retweeted":false,"possibly_sensitive":false,"possibly_sensitive_appealable":false,"lang":"en"}
