{"created_at":"Thu Jan 12 08:13:25 +0000 2017","id":819457241245855745,"id_str":"819457241245855745","text":"\u4e16\u754c\u4e2d\u306e\u5927\u597d\u304d\u3092\u96c6\u3081\u3066\u3082\u541b\u306b\u5c4a\u3051\u305f\u3044\u60f3\u3044\u306b\u8db3\u308a\u306a\u3044\uff01\uff01\uff01\uff01\uff01\n\u30b0\u30eb\u30b0\u30eb\u30ab\u30e0\u30d0\u30c3\u30af\uff01\uff01\uff01\uff01\uff3c(^o^)\uff0f","truncated":false,"entities":{"hashtags":[],"symbols":[],"user_mentions":[],"urls":[]},"source":"\u003ca href=\"http:\/\/twitter.com\/download\/iphone\" rel=\"nofollow\"\u003eTwitter for iPhone\u003c\/a\u003e","in_reply_to_status_id":null,"in_reply_to_status_id_str":null,"in_reply_to_user_id":null,"in_reply_to_user_id_str":null,"in_reply_to_screen_name":null,"user":{"id":210677300,"id_str":"210677300","name":"\u25e3 \u25e5\u25e3E l i c a\u25e5\u25e3 \u25e5","screen_name":"xx_Elitter_xx","location":"","description":"\u219120\u2191  Disney\u2764\ufe0fLove\u21e8\u9678\u5358 \u8a00\u3044\u305f\u3044\u3053\u3068\u3092\u305d\u3053\u305d\u3053\u8a00\u3046\u2b05\ufe0f\u597d\u304d\u306a\u3053\u3068\u306f\u597d\u304d\u2b05\ufe0f \u81ea\u5206\u3089\u3057\u304f( \u2022\u03c9\u2022\u0301 )\uff77\uff98 \ud83d\udc98\u4e16\u754c\u4e00\u30b7\u30e7\u30cc\u304f\u3093\u2e1c(* \u0951\ua4b3 \u0951* )\u2e1d\ud83d\udc98 \u2727\u02d6MonstaX\u25e1\u0308\u20ddVIXX\u25e1\u0308\u20ddWINNER\u2727\u02d6 #HOMMY","url":null,"entities":{"description":{"urls":[]}},"protected":false,"followers_count":184,"friends_count":629,"listed_count":13,"created_at":"Mon Nov 01 01:48:30 +0000 2010","favourites_count":4423,"utc_offset":32400,"time_zone":"Tokyo","geo_enabled":false,"verified":false,"statuses_count":179398,"lang":"ja","contributors_enabled":false,"is_translator":false,"is_translation_enabled":false,"profile_background_color":"C0DEED","profile_background_image_url":"http:\/\/pbs.twimg.com\/profile_background_images\/625453534\/210677300-ALfLz8yPODzdNlXEqeberz3xTbtfCBG226CBLcUN1129260655.jpg","profile_background_image_url_https":"https:\/\/pbs.twimg.com\/profile_background_images\/625453534\/210677300-ALfLz8yPODzdNlXEqeberz3xTbtfCBG226CBLcUN1129260655.jpg","profile_background_tile":true,"profile_image_url":"http:\/\/pbs.twimg.com\/profile_images\/720832328596004864\/OakQfU4d_normal.jpg","profile_image_url_https":"https:\/\/pbs.twimg.com\/profile_images\/720832328596004864\/OakQfU4d_normal.jpg","profile_banner_url":"https:\/\/pbs.twimg.com\/profile_banners\/210677300\/1459352555","profile_link_color":"0084B4","profile_sidebar_border_color":"C0DEED","profile_sidebar_fill_color":"DDEEF6","profile_text_color":"333333","profile_use_background_image":true,"has_extended_profile":true,"default_profile":false,"default_profile_image":false,"following":false,"follow_request_sent":false,"notifications":false,"translator_type":"none"},"geo":null,"coordinates":null,"place":null,"contributors":null,"is_quote_status":false,"retweet_count":0,"favorite_count":0,"favorited":false,"retweeted":false,"lang":"ja"}
