{"created_at":"Thu Jan 12 08:13:50 +0000 2017","id":819457345172316164,"id_str":"819457345172316164","text":"#\ud0c0\uc774\ud0c4\uac8c\uc784\n\n#\uc2a4\uc704\ud2b8\uac8c\uc784\n\n\u2663TEL :O I O - 3 4 0 8 - 2 8 8 3\n\n\u2663KAKAO: call365a\n\n\u2663\uc9c0\uc0ac\/\ucd1d\ud310\/\ub9e4\uc7a5 \uc0c1\ub2f4\uc911\n\n\u2663\uc2e0\uc6a9 \ubbff\uc74c \uce5c\uc808\n\n\u266324\uc2dc\ucf5c\uc6b4\uc601\n\n#\uba40\ud2f0\uac8c\uc784\n\n#\ud0c0\uc774\ud0c4\ub9de\uace0\n\n#\uadf8\ub79c\ub4dc\uac8c\uc784","truncated":false,"entities":{"hashtags":[{"text":"\ud0c0\uc774\ud0c4\uac8c\uc784","indices":[0,6]},{"text":"\uc2a4\uc704\ud2b8\uac8c\uc784","indices":[8,14]},{"text":"\uba40\ud2f0\uac8c\uc784","indices":[102,107]},{"text":"\ud0c0\uc774\ud0c4\ub9de\uace0","indices":[109,115]},{"text":"\uadf8\ub79c\ub4dc\uac8c\uc784","indices":[117,123]}],"symbols":[],"user_mentions":[],"urls":[]},"source":"\u003ca href=\"http:\/\/twittbot.net\/\" rel=\"nofollow\"\u003etwittbot.net\u003c\/a\u003e","in_reply_to_status_id":null,"in_reply_to_status_id_str":null,"in_reply_to_user_id":null,"in_reply_to_user_id_str":null,"in_reply_to_screen_name":null,"user":{"id":767699589923168256,"id_str":"767699589923168256","name":"\uc2a4\uc704\ud2b8\uac8c\uc784 \ubaac\uc2a4\ud130\uac8c\uc784 \uadf8\ub79c\ub4dc\uac8c\uc784","screen_name":"vpnjoosj1","location":"","description":"\uc2a4\uc704\ud2b8\uac8c\uc784 \ubaac\uc2a4\ud130\uac8c\uc784 010-3408-2883 \uba40\ud2f0\uac8c\uc784 \uadf8\ub79c\ub4dc\uac8c\uc784 \uc751\ud314\uac8c\uc784 \uc5e0\uc5d8\ube44\uac8c\uc784 \ud788\uc5b4\ub85c\uac8c\uc784 \ubc14\ub451\uc774\uc0ac\uc774\ud2b8 \ubc14\ub451\uc774\uac8c\uc784 \uc2ec\uc758\ubc14\ub451\uc774 \uc6d0\ud0c1\ubc14\ub451\uc774 \uc544\uc2dc\uc548\uce74\uc9c0\ub178 \ubca0\uac00\uc2a4\uce74\uc9c0\ub178 \ubc0d\ud0a4\ub137 \uc624\ub85c\ub77c\uac8c\uc784 \ubaa8\ubc14\uc77c\ubc14\ub451\uc774 \ubc14\uce74\ub77c\uc0ac\uc774\ud2b8 \uc2a4\uc704\ud2b8\uac8c\uc784 \uc628\ub77c\uc778\ubc14\ub451\uc774 \uc6b0\ub9ac\uce74\uc9c0\ub178 \ucc9c\uc9c0\uac8c\uc784 \ubd95\ubd95\uac8c\uc784 \ube44\ud0c0\ubbfc\uac8c\uc784 \uc2ec\uc758\ubc14\ub451\uc774","url":null,"entities":{"description":{"urls":[]}},"protected":false,"followers_count":167,"friends_count":471,"listed_count":1,"created_at":"Mon Aug 22 12:27:00 +0000 2016","favourites_count":0,"utc_offset":-28800,"time_zone":"Pacific Time (US & Canada)","geo_enabled":false,"verified":false,"statuses_count":5412,"lang":"ko","contributors_enabled":false,"is_translator":false,"is_translation_enabled":false,"profile_background_color":"F5F8FA","profile_background_image_url":null,"profile_background_image_url_https":null,"profile_background_tile":false,"profile_image_url":"http:\/\/pbs.twimg.com\/profile_images\/781025626752946176\/hhpFD9tk_normal.jpg","profile_image_url_https":"https:\/\/pbs.twimg.com\/profile_images\/781025626752946176\/hhpFD9tk_normal.jpg","profile_banner_url":"https:\/\/pbs.twimg.com\/profile_banners\/767699589923168256\/1475045972","profile_link_color":"1DA1F2","profile_sidebar_border_color":"C0DEED","profile_sidebar_fill_color":"DDEEF6","profile_text_color":"333333","profile_use_background_image":true,"has_extended_profile":false,"default_profile":true,"default_profile_image":false,"following":false,"follow_request_sent":false,"notifications":false,"translator_type":"none"},"geo":null,"coordinates":null,"place":null,"contributors":null,"is_quote_status":false,"retweet_count":0,"favorite_count":0,"favorited":false,"retweeted":false,"lang":"ko"}
