{"created_at":"Thu Jan 12 08:13:20 +0000 2017","id":819457219037011969,"id_str":"819457219037011969","text":"@kwamenace @ShitJokes I get it now cheers","truncated":false,"entities":{"hashtags":[],"symbols":[],"user_mentions":[{"screen_name":"kwamenace","name":"Steve","id":466505286,"id_str":"466505286","indices":[0,10]},{"screen_name":"ShitJokes","name":"Shit Jokes","id":3592010423,"id_str":"3592010423","indices":[11,21]}],"urls":[]},"source":"\u003ca href=\"http:\/\/twitter.com\/download\/android\" rel=\"nofollow\"\u003eTwitter for Android\u003c\/a\u003e","in_reply_to_status_id":819279776540196864,"in_reply_to_status_id_str":"819279776540196864","in_reply_to_user_id":466505286,"in_reply_to_user_id_str":"466505286","in_reply_to_screen_name":"kwamenace","user":{"id":21746010,"id_str":"21746010","name":"Jonny Liebenberg","screen_name":"JonnyLiebenberg","location":"Melbourne, Australia","description":"Husband and father. Passionate and opinionated lover of running, sport, podcasts, reading, writing, movies and music! All opinions are my own.","url":null,"entities":{"description":{"urls":[]}},"protected":false,"followers_count":737,"friends_count":2290,"listed_count":32,"created_at":"Tue Feb 24 11:26:42 +0000 2009","favourites_count":694,"utc_offset":39600,"time_zone":"Melbourne","geo_enabled":true,"verified":false,"statuses_count":7438,"lang":"en","contributors_enabled":false,"is_translator":false,"is_translation_enabled":false,"profile_background_color":"1A1B1F","profile_background_image_url":"http:\/\/abs.twimg.com\/images\/themes\/theme9\/bg.gif","profile_background_image_url_https":"https:\/\/abs.twimg.com\/images\/themes\/theme9\/bg.gif","profile_background_tile":false,"profile_image_url":"http:\/\/pbs.twimg.com\/profile_images\/488461789416267776\/6woqJJcb_normal.jpeg","profile_image_url_https":"https:\/\/pbs.twimg.com\/profile_images\/488461789416267776\/6woqJJcb_normal.jpeg","profile_banner_url":"https:\/\/pbs.twimg.com\/profile_banners\/21746010\/1405365616","profile_link_color":"2FC2EF","profile_sidebar_border_color":"181A1E","profile_sidebar_fill_color":"252429","profile_text_color":"666666","profile_use_background_image":true,"has_extended_profile":false,"default_profile":false,"default_profile_image":false,"following":false,"follow_request_sent":false,"notifications":false,"translator_type":"none"},"geo":null,"coordinates":null,"place":{"id":"01864a8a64df9dc4","url":"https:\/\/api.twitter.com\/1.1\/geo\/id\/01864a8a64df9dc4.json","place_type":"city","name":"Melbourne","full_name":"Melbourne, Victoria","country_code":"AU","country":"Australia","contained_within":[],"bounding_box":{"type":"Polygon","coordinates":[[[144.593741856,-38.433859306],[145.512528832,-38.433859306],[145.512528832,-37.5112737225],[144.593741856,-37.5112737225]]]},"attributes":{}},"contributors":null,"is_quote_status":false,"retweet_count":0,"favorite_count":0,"favorited":false,"retweeted":false,"lang":"en"}
