{"created_at":"Thu Jan 12 08:13:15 +0000 2017","id":819457199772577793,"id_str":"819457199772577793","text":"okay but at least you have the cards so i just need to make them beefy","truncated":false,"entities":{"hashtags":[],"symbols":[],"user_mentions":[],"urls":[]},"source":"\u003ca href=\"https:\/\/about.twitter.com\/products\/tweetdeck\" rel=\"nofollow\"\u003eTweetDeck\u003c\/a\u003e","in_reply_to_status_id":null,"in_reply_to_status_id_str":null,"in_reply_to_user_id":null,"in_reply_to_user_id_str":null,"in_reply_to_screen_name":null,"user":{"id":224560354,"id_str":"224560354","name":"uv \u2b50\ufe0f @ \u84ee\u5df3\u656c\u4eba\u306eATM","screen_name":"inocciduous","location":"nikki | (she) | 20+ | gmt-10","description":"adj. not harmful or offensive \u2601 I simply met someone who is much more interesting than any manga protagonist. \ud83c\udf3f HIATUS | LIKES\/RTS ONLY | @ or DM TO CONTACT","url":"https:\/\/t.co\/BaMEvI7dVm","entities":{"url":{"urls":[{"url":"https:\/\/t.co\/BaMEvI7dVm","expanded_url":"http:\/\/twpf.jp\/inocciduous","display_url":"twpf.jp\/inocciduous","indices":[0,23]}]},"description":{"urls":[]}},"protected":false,"followers_count":258,"friends_count":368,"listed_count":26,"created_at":"Thu Dec 09 09:09:42 +0000 2010","favourites_count":85776,"utc_offset":-36000,"time_zone":"Hawaii","geo_enabled":false,"verified":false,"statuses_count":134889,"lang":"en","contributors_enabled":false,"is_translator":false,"is_translation_enabled":false,"profile_background_color":"E8FCEC","profile_background_image_url":"http:\/\/pbs.twimg.com\/profile_background_images\/378800000111447043\/e6cf0646d0c70aa6bf524dd333eb121b.jpeg","profile_background_image_url_https":"https:\/\/pbs.twimg.com\/profile_background_images\/378800000111447043\/e6cf0646d0c70aa6bf524dd333eb121b.jpeg","profile_background_tile":true,"profile_image_url":"http:\/\/pbs.twimg.com\/profile_images\/813634473279385600\/mmC1-pGt_normal.jpg","profile_image_url_https":"https:\/\/pbs.twimg.com\/profile_images\/813634473279385600\/mmC1-pGt_normal.jpg","profile_banner_url":"https:\/\/pbs.twimg.com\/profile_banners\/224560354\/1482846365","profile_link_color":"FABBBB","profile_sidebar_border_color":"FFFFFF","profile_sidebar_fill_color":"D7FFB8","profile_text_color":"555555","profile_use_background_image":true,"has_extended_profile":true,"default_profile":false,"default_profile_image":false,"following":false,"follow_request_sent":false,"notifications":false,"translator_type":"none"},"geo":null,"coordinates":null,"place":null,"contributors":null,"is_quote_status":false,"retweet_count":0,"favorite_count":0,"favorited":false,"retweeted":false,"lang":"en"}
