{"created_at":"Thu Jan 12 08:13:10 +0000 2017","id":819457176812949506,"id_str":"819457176812949506","text":"I've been listening to @gwatsky some more times and so should you xP\nhttps:\/\/t.co\/IM7MmjPf50","truncated":false,"entities":{"hashtags":[],"symbols":[],"user_mentions":[{"screen_name":"gwatsky","name":"Watsky","id":103467620,"id_str":"103467620","indices":[23,31]}],"urls":[{"url":"https:\/\/t.co\/IM7MmjPf50","expanded_url":"https:\/\/youtu.be\/xKLRGJYna-8","display_url":"youtu.be\/xKLRGJYna-8","indices":[69,92]}]},"source":"\u003ca href=\"http:\/\/twitter.com\/download\/android\" rel=\"nofollow\"\u003eTwitter for Android\u003c\/a\u003e","in_reply_to_status_id":null,"in_reply_to_status_id_str":null,"in_reply_to_user_id":null,"in_reply_to_user_id_str":null,"in_reply_to_screen_name":null,"user":{"id":30797363,"id_str":"30797363","name":"c\u043da\u0455e ed\u043cond\u0455on","screen_name":"ChaseEdmondson","location":"Hollywood","description":"Actor\/Producer\/VR Enthusiast","url":"https:\/\/t.co\/F5aYS27pnM","entities":{"url":{"urls":[{"url":"https:\/\/t.co\/F5aYS27pnM","expanded_url":"http:\/\/ChaseEdmondson.com","display_url":"ChaseEdmondson.com","indices":[0,23]}]},"description":{"urls":[]}},"protected":false,"followers_count":863,"friends_count":467,"listed_count":37,"created_at":"Mon Apr 13 03:28:18 +0000 2009","favourites_count":4589,"utc_offset":-21600,"time_zone":"Central Time (US & Canada)","geo_enabled":true,"verified":false,"statuses_count":9221,"lang":"en","contributors_enabled":false,"is_translator":false,"is_translation_enabled":false,"profile_background_color":"000000","profile_background_image_url":"http:\/\/pbs.twimg.com\/profile_background_images\/77731042\/hat.jpg","profile_background_image_url_https":"https:\/\/pbs.twimg.com\/profile_background_images\/77731042\/hat.jpg","profile_background_tile":false,"profile_image_url":"http:\/\/pbs.twimg.com\/profile_images\/748610358621794304\/vYH2SUkL_normal.jpg","profile_image_url_https":"https:\/\/pbs.twimg.com\/profile_images\/748610358621794304\/vYH2SUkL_normal.jpg","profile_banner_url":"https:\/\/pbs.twimg.com\/profile_banners\/30797363\/1471506973","profile_link_color":"A10000","profile_sidebar_border_color":"FFFFFF","profile_sidebar_fill_color":"636363","profile_text_color":"292929","profile_use_background_image":true,"has_extended_profile":false,"default_profile":false,"default_profile_image":false,"following":false,"follow_request_sent":false,"notifications":false,"translator_type":"none"},"geo":null,"coordinates":null,"place":{"id":"3b77caf94bfc81fe","url":"https:\/\/api.twitter.com\/1.1\/geo\/id\/3b77caf94bfc81fe.json","place_type":"city","name":"Los Angeles","full_name":"Los Angeles, CA","country_code":"US","country":"United States","contained_within":[],"bounding_box":{"type":"Polygon","coordinates":[[[-118.668404,33.704538],[-118.155409,33.704538],[-118.155409,34.337041],[-118.668404,34.337041]]]},"attributes":{}},"contributors":null,"is_quote_status":false,"retweet_count":0,"favorite_count":1,"favorited":false,"retweeted":false,"possibly_sensitive":false,"possibly_sensitive_appealable":false,"lang":"en"}
