{"created_at":"Thu Jan 12 08:13:30 +0000 2017","id":819457259881144320,"id_str":"819457259881144320","text":"https:\/\/t.co\/RV5L82Roo0","truncated":false,"entities":{"hashtags":[],"symbols":[],"user_mentions":[],"urls":[],"media":[{"id":819457230596554752,"id_str":"819457230596554752","indices":[0,23],"media_url":"http:\/\/pbs.twimg.com\/media\/C19MAnJVQAAVcIr.jpg","media_url_https":"https:\/\/pbs.twimg.com\/media\/C19MAnJVQAAVcIr.jpg","url":"https:\/\/t.co\/RV5L82Roo0","display_url":"pic.twitter.com\/RV5L82Roo0","expanded_url":"https:\/\/twitter.com\/Nori_jabduck\/status\/819457259881144320\/photo\/1","type":"photo","sizes":{"thumb":{"w":150,"h":150,"resize":"crop"},"small":{"w":643,"h":659,"resize":"fit"},"medium":{"w":643,"h":659,"resize":"fit"},"large":{"w":643,"h":659,"resize":"fit"}}}]},"extended_entities":{"media":[{"id":819457230596554752,"id_str":"819457230596554752","indices":[0,23],"media_url":"http:\/\/pbs.twimg.com\/media\/C19MAnJVQAAVcIr.jpg","media_url_https":"https:\/\/pbs.twimg.com\/media\/C19MAnJVQAAVcIr.jpg","url":"https:\/\/t.co\/RV5L82Roo0","display_url":"pic.twitter.com\/RV5L82Roo0","expanded_url":"https:\/\/twitter.com\/Nori_jabduck\/status\/819457259881144320\/photo\/1","type":"photo","sizes":{"thumb":{"w":150,"h":150,"resize":"crop"},"small":{"w":643,"h":659,"resize":"fit"},"medium":{"w":643,"h":659,"resize":"fit"},"large":{"w":643,"h":659,"resize":"fit"}}}]},"source":"\u003ca href=\"http:\/\/twitter.com\/download\/android\" rel=\"nofollow\"\u003eTwitter for Android\u003c\/a\u003e","in_reply_to_status_id":null,"in_reply_to_status_id_str":null,"in_reply_to_user_id":null,"in_reply_to_user_id_str":null,"in_reply_to_screen_name":null,"user":{"id":712278138345037824,"id_str":"712278138345037824","name":"\uc6b0\uc2dc\uc9c0\ub9c8 \uac00\uc2b4\ub9cc\uc9c4\ub2e4","screen_name":"Nori_jabduck","location":"\ud504\ub85c\ud544\u2b07\ub9de\ud314:\ud2b8\uce5c\uc18c,\uc120\ud314\uc120\uba58.\uc774\ubcc4:\ube14\uc5b8\ube14","description":"\uc544 \ucd71\uce90\ucefe\ub4e4 \ub5a1\uce58\ub294 \uce68\ub300\uc606 \ud654\ubd84\uc774 \ub418\uace0\uc2f6\ub2e4\n\n\n\n\n\n\n\n\n\ud5e4\ub354: \ucdcc\ub2d8( @hnk6705432 )","url":"https:\/\/t.co\/jHpOt55dCg","entities":{"url":{"urls":[{"url":"https:\/\/t.co\/jHpOt55dCg","expanded_url":"https:\/\/www.evernote.com\/shard\/s357\/sh\/7bcfdf52-a807-42cb-8c6a-5a32ceaf4b18\/9cadf456343ae7791e7b9a4a","display_url":"evernote.com\/shard\/s357\/sh\/\u2026","indices":[0,23]}]},"description":{"urls":[]}},"protected":false,"followers_count":139,"friends_count":95,"listed_count":9,"created_at":"Tue Mar 22 14:01:56 +0000 2016","favourites_count":21507,"utc_offset":-28800,"time_zone":"Pacific Time (US & Canada)","geo_enabled":false,"verified":false,"statuses_count":63351,"lang":"ko","contributors_enabled":false,"is_translator":false,"is_translation_enabled":false,"profile_background_color":"000000","profile_background_image_url":"http:\/\/abs.twimg.com\/images\/themes\/theme1\/bg.png","profile_background_image_url_https":"https:\/\/abs.twimg.com\/images\/themes\/theme1\/bg.png","profile_background_tile":false,"profile_image_url":"http:\/\/pbs.twimg.com\/profile_images\/819507498788876288\/B20BoyYu_normal.jpg","profile_image_url_https":"https:\/\/pbs.twimg.com\/profile_images\/819507498788876288\/B20BoyYu_normal.jpg","profile_banner_url":"https:\/\/pbs.twimg.com\/profile_banners\/712278138345037824\/1483965635","profile_link_color":"E81C4F","profile_sidebar_border_color":"000000","profile_sidebar_fill_color":"000000","profile_text_color":"000000","profile_use_background_image":false,"has_extended_profile":true,"default_profile":false,"default_profile_image":false,"following":false,"follow_request_sent":false,"notifications":false,"translator_type":"none"},"geo":null,"coordinates":null,"place":null,"contributors":null,"is_quote_status":false,"retweet_count":0,"favorite_count":0,"favorited":false,"retweeted":false,"possibly_sensitive":false,"possibly_sensitive_appealable":false,"lang":"und"}
