{"created_at":"Thu Jan 12 08:13:45 +0000 2017","id":819457322066001921,"id_str":"819457322066001921","text":"i'm weak https:\/\/t.co\/m7W4WzuAmE","truncated":false,"entities":{"hashtags":[],"symbols":[],"user_mentions":[],"urls":[{"url":"https:\/\/t.co\/m7W4WzuAmE","expanded_url":"https:\/\/twitter.com\/beyondselu\/status\/819114715188252672","display_url":"twitter.com\/beyondselu\/sta\u2026","indices":[9,32]}]},"source":"\u003ca href=\"http:\/\/twitter.com\/download\/android\" rel=\"nofollow\"\u003eTwitter for Android\u003c\/a\u003e","in_reply_to_status_id":null,"in_reply_to_status_id_str":null,"in_reply_to_user_id":null,"in_reply_to_user_id_str":null,"in_reply_to_screen_name":null,"user":{"id":2693841990,"id_str":"2693841990","name":"mar | nini day","screen_name":"kmarpanda","location":"manur is real","description":"@kmsissues: u are the supreme goddess of the kvillage u should be proud","url":"https:\/\/t.co\/hs1Jugi5sD","entities":{"url":{"urls":[{"url":"https:\/\/t.co\/hs1Jugi5sD","expanded_url":"https:\/\/curiouscat.me\/kmarpanda","display_url":"curiouscat.me\/kmarpanda","indices":[0,23]}]},"description":{"urls":[]}},"protected":false,"followers_count":764,"friends_count":407,"listed_count":27,"created_at":"Wed Jul 30 20:29:12 +0000 2014","favourites_count":4919,"utc_offset":3600,"time_zone":"Madrid","geo_enabled":true,"verified":false,"statuses_count":15888,"lang":"es","contributors_enabled":false,"is_translator":false,"is_translation_enabled":true,"profile_background_color":"000000","profile_background_image_url":"http:\/\/pbs.twimg.com\/profile_background_images\/625371795814793216\/olflBbDX.jpg","profile_background_image_url_https":"https:\/\/pbs.twimg.com\/profile_background_images\/625371795814793216\/olflBbDX.jpg","profile_background_tile":true,"profile_image_url":"http:\/\/pbs.twimg.com\/profile_images\/819930551725518848\/wd8FVR7j_normal.jpg","profile_image_url_https":"https:\/\/pbs.twimg.com\/profile_images\/819930551725518848\/wd8FVR7j_normal.jpg","profile_banner_url":"https:\/\/pbs.twimg.com\/profile_banners\/2693841990\/1480318270","profile_link_color":"809496","profile_sidebar_border_color":"000000","profile_sidebar_fill_color":"000000","profile_text_color":"000000","profile_use_background_image":true,"has_extended_profile":true,"default_profile":false,"default_profile_image":false,"following":false,"follow_request_sent":false,"notifications":false,"translator_type":"none"},"geo":null,"coordinates":null,"place":null,"contributors":null,"is_quote_status":true,"quoted_status_id":819114715188252672,"quoted_status_id_str":"819114715188252672","quoted_status":{"created_at":"Wed Jan 11 09:32:21 +0000 2017","id":819114715188252672,"id_str":"819114715188252672","text":"HOLD ON TIGHT PLEASE https:\/\/t.co\/cYnsj36rS7","truncated":false,"entities":{"hashtags":[],"symbols":[],"user_mentions":[],"urls":[],"media":[{"id":819114638298124288,"id_str":"819114638298124288","indices":[21,44],"media_url":"http:\/\/pbs.twimg.com\/media\/C14UbHYVEAAVj4T.jpg","media_url_https":"https:\/\/pbs.twimg.com\/media\/C14UbHYVEAAVj4T.jpg","url":"https:\/\/t.co\/cYnsj36rS7","display_url":"pic.twitter.com\/cYnsj36rS7","expanded_url":"https:\/\/twitter.com\/beyondselu\/status\/819114715188252672\/photo\/1","type":"photo","sizes":{"large":{"w":1024,"h":562,"resize":"fit"},"small":{"w":680,"h":373,"resize":"fit"},"thumb":{"w":150,"h":150,"resize":"crop"},"medium":{"w":1024,"h":562,"resize":"fit"}}}]},"extended_entities":{"media":[{"id":819114638298124288,"id_str":"819114638298124288","indices":[21,44],"media_url":"http:\/\/pbs.twimg.com\/media\/C14UbHYVEAAVj4T.jpg","media_url_https":"https:\/\/pbs.twimg.com\/media\/C14UbHYVEAAVj4T.jpg","url":"https:\/\/t.co\/cYnsj36rS7","display_url":"pic.twitter.com\/cYnsj36rS7","expanded_url":"https:\/\/twitter.com\/beyondselu\/status\/819114715188252672\/photo\/1","type":"photo","sizes":{"large":{"w":1024,"h":562,"resize":"fit"},"small":{"w":680,"h":373,"resize":"fit"},"thumb":{"w":150,"h":150,"resize":"crop"},"medium":{"w":1024,"h":562,"resize":"fit"}}},{"id":819114649983414272,"id_str":"819114649983414272","indices":[21,44],"media_url":"http:\/\/pbs.twimg.com\/media\/C14Uby6UcAA6mGl.jpg","media_url_https":"https:\/\/pbs.twimg.com\/media\/C14Uby6UcAA6mGl.jpg","url":"https:\/\/t.co\/cYnsj36rS7","display_url":"pic.twitter.com\/cYnsj36rS7","expanded_url":"https:\/\/twitter.com\/beyondselu\/status\/819114715188252672\/photo\/1","type":"photo","sizes":{"medium":{"w":801,"h":1200,"resize":"fit"},"thumb":{"w":150,"h":150,"resize":"crop"},"large":{"w":801,"h":1200,"resize":"fit"},"small":{"w":454,"h":680,"resize":"fit"}}},{"id":819114679553273856,"id_str":"819114679553273856","indices":[21,44],"media_url":"http:\/\/pbs.twimg.com\/media\/C14UdhEUsAA8jJh.jpg","media_url_https":"https:\/\/pbs.twimg.com\/media\/C14UdhEUsAA8jJh.jpg","url":"https:\/\/t.co\/cYnsj36rS7","display_url":"pic.twitter.com\/cYnsj36rS7","expanded_url":"https:\/\/twitter.com\/beyondselu\/status\/819114715188252672\/photo\/1","type":"photo","sizes":{"small":{"w":680,"h":454,"resize":"fit"},"thumb":{"w":150,"h":150,"resize":"crop"},"medium":{"w":1024,"h":683,"resize":"fit"},"large":{"w":1024,"h":683,"resize":"fit"}}},{"id":819114697911734272,"id_str":"819114697911734272","indices":[21,44],"media_url":"http:\/\/pbs.twimg.com\/media\/C14UeldUkAAQtjX.jpg","media_url_https":"https:\/\/pbs.twimg.com\/media\/C14UeldUkAAQtjX.jpg","url":"https:\/\/t.co\/cYnsj36rS7","display_url":"pic.twitter.com\/cYnsj36rS7","expanded_url":"https:\/\/twitter.com\/beyondselu\/status\/819114715188252672\/photo\/1","type":"photo","sizes":{"large":{"w":948,"h":1024,"resize":"fit"},"small":{"w":630,"h":680,"resize":"fit"},"thumb":{"w":150,"h":150,"resize":"crop"},"medium":{"w":948,"h":1024,"resize":"fit"}}}]},"source":"\u003ca href=\"http:\/\/twitter.com\" rel=\"nofollow\"\u003eTwitter Web Client\u003c\/a\u003e","in_reply_to_status_id":null,"in_reply_to_status_id_str":null,"in_reply_to_user_id":null,"in_reply_to_user_id_str":null,"in_reply_to_screen_name":null,"user":{"id":1266786450,"id_str":"1266786450","name":"hun","screen_name":"beyondselu","location":"\uc5d1\uc18c\u2661 \ucc2c\uc218\u2661 nct - \uc9c0\uc131\u2661 ","description":"When there are difficulties, hold tight onto my hand. You have me, you don't have to be afraid. \u02d7\u02cb\u02cf\ub0b4 \uc6b0\uc8fc\ub294 \uc804\ubd80 \ub108\uc57c 940412 \u2661 \u02ce\u02ca\u02d7","url":null,"entities":{"description":{"urls":[]}},"protected":false,"followers_count":27112,"friends_count":179,"listed_count":164,"created_at":"Thu Mar 14 11:06:34 +0000 2013","favourites_count":10007,"utc_offset":28800,"time_zone":"Beijing","geo_enabled":true,"verified":false,"statuses_count":71465,"lang":"en","contributors_enabled":false,"is_translator":false,"is_translation_enabled":false,"profile_background_color":"EEFF03","profile_background_image_url":"http:\/\/pbs.twimg.com\/profile_background_images\/546283584995074048\/Qbm1p-zO.jpeg","profile_background_image_url_https":"https:\/\/pbs.twimg.com\/profile_background_images\/546283584995074048\/Qbm1p-zO.jpeg","profile_background_tile":true,"profile_image_url":"http:\/\/pbs.twimg.com\/profile_images\/811522647418777600\/NcEls3NJ_normal.jpg","profile_image_url_https":"https:\/\/pbs.twimg.com\/profile_images\/811522647418777600\/NcEls3NJ_normal.jpg","profile_banner_url":"https:\/\/pbs.twimg.com\/profile_banners\/1266786450\/1482316768","profile_link_color":"278787","profile_sidebar_border_color":"FFFFFF","profile_sidebar_fill_color":"DDEEF6","profile_text_color":"333333","profile_use_background_image":true,"has_extended_profile":false,"default_profile":false,"default_profile_image":false,"following":false,"follow_request_sent":false,"notifications":false,"translator_type":"none"},"geo":null,"coordinates":null,"place":null,"contributors":null,"is_quote_status":false,"retweet_count":1068,"favorite_count":879,"favorited":false,"retweeted":false,"possibly_sensitive":false,"possibly_sensitive_appealable":false,"lang":"en"},"retweet_count":0,"favorite_count":1,"favorited":false,"retweeted":false,"possibly_sensitive":false,"possibly_sensitive_appealable":false,"lang":"en"}
